[
  {
    "awid": "22222222222222222222222222222222",
    "patientId": "PAT-1006",
    "doctorId": "DOC-005",
    "dateTime": "2025-12-20T18:00:00.000Z",
    "status": "Completed",
    "note": "Previous checkup - went well",
    "sys": {
      "cts": "2025-12-03T16:19:53.675Z",
      "mts": "2025-12-03T16:19:53.675Z",
      "rev": 0,
      "uuObjectType": "appointment"
    },
    "oid": "693063296a854f19658293d2",
    "id": "693063296a854f19658293d2"
  },
  {
    "awid": "22222222222222222222222222222222",
    "patientId": "PAT-1004",
    "doctorId": "DOC-007",
    "dateTime": "2025-12-22T15:45:00.000Z",
    "status": "Completed",
    "note": "Annual physical exam.",
    "sys": {
      "cts": "2025-12-03T16:19:53.675Z",
      "mts": "2025-12-03T16:19:53.675Z",
      "rev": 0,
      "uuObjectType": "appointment"
    },
    "oid": "693063296a854f19658293d3",
    "id": "693063296a854f19658293d3"
  },
  {
    "awid": "22222222222222222222222222222222",
    "patientId": "PAT-1002",
    "doctorId": "DOC-005",
    "dateTime": "2025-12-28T13:30:00.000Z",
    "status": "Confirmed",
    "note": "Routine check-up regarding blood pressure.",
    "sys": {
      "cts": "2025-12-03T16:19:53.675Z",
      "mts": "2025-12-03T16:19:53.675Z",
      "rev": 0,
      "uuObjectType": "appointment"
    },
    "oid": "693063296a854f19658293d4",
    "id": "693063296a854f19658293d4"
  },
  {
    "awid": "22222222222222222222222222222222",
    "patientId": "PAT-1001",
    "doctorId": "DOC-001",
    "dateTime": "2025-12-30T15:00:00.000Z",
    "status": "Confirmed",
    "note": "Follow-up on prescribed medication.",
    "sys": {
      "cts": "2025-12-03T16:19:53.675Z",
      "mts": "2025-12-03T16:19:53.675Z",
      "rev": 0,
      "uuObjectType": "appointment"
    },
    "oid": "693063296a854f19658293d5",
    "id": "693063296a854f19658293d5"
  },
  {
    "awid": "22222222222222222222222222222222",
    "patientId": "PAT-1003",
    "doctorId": "DOC-005",
    "dateTime": "2025-12-24T18:30:00.000Z",
    "status": "Cancelled",
    "note": "Patient called to reschedule due to work conflict.",
    "sys": {
      "cts": "2025-12-03T16:19:53.675Z",
      "mts": "2025-12-03T16:19:53.675Z",
      "rev": 0,
      "uuObjectType": "appointment"
    },
    "oid": "693063296a854f19658293d6",
    "id": "693063296a854f19658293d6"
  },
  {
    "awid": "22222222222222222222222222222222",
    "patientId": "PAT-1005",
    "doctorId": "DOC-002",
    "dateTime": "2026-01-02T13:15:00.000Z",
    "status": "Confirmed",
    "note": "Consultation for persistent headaches.",
    "sys": {
      "cts": "2025-12-03T16:19:53.675Z",
      "mts": "2025-12-03T16:19:53.675Z",
      "rev": 0,
      "uuObjectType": "appointment"
    },
    "oid": "693063296a854f19658293d7",
    "id": "693063296a854f19658293d7"
  },
  {
    "awid": "22222222222222222222222222222222",
    "patientId": "PAT-1002",
    "doctorId": "DOC-008",
    "dateTime": "2025-12-25T20:30:00.000Z",
    "status": "Cancelled",
    "note": "Doctor unavailable, rescheduled to next week.",
    "sys": {
      "cts": "2025-12-03T16:19:53.675Z",
      "mts": "2025-12-03T16:19:53.675Z",
      "rev": 0,
      "uuObjectType": "appointment"
    },
    "oid": "693063296a854f19658293d9",
    "id": "693063296a854f19658293d9"
  },
  {
    "awid": "22222222222222222222222222222222",
    "patientId": "PAT-1007",
    "doctorId": "DOC-006",
    "dateTime": "2026-01-05T14:00:00.000Z",
    "status": "Confirmed",
    "note": "Initial consultation for knee pain.",
    "sys": {
      "cts": "2025-12-03T16:19:53.675Z",
      "mts": "2025-12-03T16:19:53.675Z",
      "rev": 0,
      "uuObjectType": "appointment"
    },
    "oid": "693063296a854f19658293da",
    "id": "693063296a854f19658293da"
  },
  {
    "awid": "22222222222222222222222222222222",
    "patientId": "PAT-1008",
    "doctorId": "DOC-002",
    "dateTime": "2026-01-10T14:30:00.000Z",
    "status": "Confirmed",
    "note": "Vaccination update.",
    "sys": {
      "cts": "2025-12-03T16:19:53.675Z",
      "mts": "2025-12-03T16:19:53.675Z",
      "rev": 0,
      "uuObjectType": "appointment"
    },
    "oid": "693063296a854f19658293db",
    "id": "693063296a854f19658293db"
  },
  {
    "awid": "22222222222222222222222222222222",
    "patientId": "PAT-1002",
    "doctorId": "DOC-001",
    "dateTime": "2025-12-31T10:00:00.000Z",
    "status": "Confirmed",
    "note": "Cardiac check-up",
    "sys": {
      "cts": "2025-12-29T12:00:00.000Z",
      "mts": "2025-12-29T12:00:00.000Z",
      "rev": 0,
      "uuObjectType": "appointment"
    },
    "oid": "693063296a854f19658293dc",
    "id": "693063296a854f19658293dc"
  },
  {
    "awid": "22222222222222222222222222222222",
    "patientId": "PAT-1003",
    "doctorId": "DOC-001",
    "dateTime": "2026-01-03T14:00:00.000Z",
    "status": "Confirmed",
    "note": "Follow-up appointment",
    "sys": {
      "cts": "2025-12-29T12:00:00.000Z",
      "mts": "2025-12-29T12:00:00.000Z",
      "rev": 0,
      "uuObjectType": "appointment"
    },
    "oid": "693063296a854f19658293dd",
    "id": "693063296a854f19658293dd"
  },
  {
    "awid": "22222222222222222222222222222222",
    "patientId": "PAT-1004",
    "doctorId": "DOC-001",
    "dateTime": "2026-01-08T09:00:00.000Z",
    "status": "Confirmed",
    "note": "Consultation",
    "sys": {
      "cts": "2025-12-29T12:00:00.000Z",
      "mts": "2025-12-29T12:00:00.000Z",
      "rev": 0,
      "uuObjectType": "appointment"
    },
    "oid": "693063296a854f19658293de",
    "id": "693063296a854f19658293de"
  },
  {
    "awid": "22222222222222222222222222222222",
    "patientId": "PAT-1001",
    "doctorId": "DOC-002",
    "dateTime": "2025-12-31T11:00:00.000Z",
    "status": "Confirmed",
    "note": "General check-up",
    "sys": {
      "cts": "2025-12-29T12:00:00.000Z",
      "mts": "2025-12-29T12:00:00.000Z",
      "rev": 0,
      "uuObjectType": "appointment"
    },
    "oid": "693063296a854f19658293df",
    "id": "693063296a854f19658293df"
  },
  {
    "awid": "22222222222222222222222222222222",
    "patientId": "PAT-1001",
    "doctorId": "DOC-003",
    "dateTime": "2026-01-04T13:00:00.000Z",
    "status": "Confirmed",
    "note": "Skin issue consultation",
    "sys": {
      "cts": "2025-12-29T12:00:00.000Z",
      "mts": "2025-12-29T12:00:00.000Z",
      "rev": 0,
      "uuObjectType": "appointment"
    },
    "oid": "693063296a854f19658293e0",
    "id": "693063296a854f19658293e0"
  },
  {
    "awid": "22222222222222222222222222222222",
    "patientId": "PAT-1001",
    "doctorId": "DOC-004",
    "dateTime": "2026-01-09T15:00:00.000Z",
    "status": "Confirmed",
    "note": "Orthopedic consultation",
    "sys": {
      "cts": "2025-12-29T12:00:00.000Z",
      "mts": "2025-12-29T12:00:00.000Z",
      "rev": 0,
      "uuObjectType": "appointment"
    },
    "oid": "693063296a854f19658293e1",
    "id": "693063296a854f19658293e1"
  },
  {
    "awid": "22222222222222222222222222222222",
    "patientId": "PAT-1005",
    "doctorId": "DOC-001",
    "dateTime": "2025-12-15T11:00:00.000Z",
    "status": "Completed",
    "note": "Heart exam",
    "sys": {
      "cts": "2025-12-29T12:00:00.000Z",
      "mts": "2025-12-29T12:00:00.000Z",
      "rev": 0,
      "uuObjectType": "appointment"
    },
    "oid": "693063296a854f19658293e2",
    "id": "693063296a854f19658293e2"
  },
  {
    "awid": "22222222222222222222222222222222",
    "patientId": "PAT-1006",
    "doctorId": "DOC-001",
    "dateTime": "2026-01-15T09:30:00.000Z",
    "status": "Confirmed",
    "note": "Routine check-up",
    "sys": {
      "cts": "2025-12-29T12:00:00.000Z",
      "mts": "2025-12-29T12:00:00.000Z",
      "rev": 0,
      "uuObjectType": "appointment"
    },
    "oid": "693063296a854f19658293e3",
    "id": "693063296a854f19658293e3"
  },
  {
    "awid": "22222222222222222222222222222222",
    "patientId": "PAT-1007",
    "doctorId": "DOC-001",
    "dateTime": "2026-01-20T14:00:00.000Z",
    "status": "Cancelled",
    "note": "Patient rescheduled",
    "sys": {
      "cts": "2025-12-29T12:00:00.000Z",
      "mts": "2025-12-29T12:00:00.000Z",
      "rev": 0,
      "uuObjectType": "appointment"
    },
    "oid": "693063296a854f19658293e4",
    "id": "693063296a854f19658293e4"
  },
  {
    "awid": "22222222222222222222222222222222",
    "patientId": "PAT-1008",
    "doctorId": "DOC-001",
    "dateTime": "2025-12-10T10:00:00.000Z",
    "status": "Completed",
    "note": "Follow-up on treatment",
    "sys": {
      "cts": "2025-12-29T12:00:00.000Z",
      "mts": "2025-12-29T12:00:00.000Z",
      "rev": 0,
      "uuObjectType": "appointment"
    },
    "oid": "693063296a854f19658293e5",
    "id": "693063296a854f19658293e5"
  },
  {
    "awid": "22222222222222222222222222222222",
    "patientId": "PAT-1001",
    "doctorId": "DOC-005",
    "dateTime": "2025-12-20T16:00:00.000Z",
    "status": "Completed",
    "note": "Internal medicine check",
    "sys": {
      "cts": "2025-12-29T12:00:00.000Z",
      "mts": "2025-12-29T12:00:00.000Z",
      "rev": 0,
      "uuObjectType": "appointment"
    },
    "oid": "693063296a854f19658293e6",
    "id": "693063296a854f19658293e6"
  },
  {
    "awid": "22222222222222222222222222222222",
    "patientId": "PAT-1001",
    "doctorId": "DOC-006",
    "dateTime": "2026-01-12T13:00:00.000Z",
    "status": "Confirmed",
    "note": "Neurology consultation",
    "sys": {
      "cts": "2025-12-29T12:00:00.000Z",
      "mts": "2025-12-29T12:00:00.000Z",
      "rev": 0,
      "uuObjectType": "appointment"
    },
    "oid": "693063296a854f19658293e7",
    "id": "693063296a854f19658293e7"
  },
  {
    "awid": "22222222222222222222222222222222",
    "patientId": "PAT-1001",
    "doctorId": "DOC-007",
    "dateTime": "2026-01-18T11:00:00.000Z",
    "status": "Cancelled",
    "note": "Cancelled by patient",
    "sys": {
      "cts": "2025-12-29T12:00:00.000Z",
      "mts": "2025-12-29T12:00:00.000Z",
      "rev": 0,
      "uuObjectType": "appointment"
    },
    "oid": "693063296a854f19658293e8",
    "id": "693063296a854f19658293e8"
  },
  {
    "awid": "22222222222222222222222222222222",
    "patientId": "PAT-1001",
    "doctorId": "DOC-008",
    "dateTime": "2025-12-25T17:00:00.000Z",
    "status": "Completed",
    "note": "Psychiatry session",
    "sys": {
      "cts": "2025-12-29T12:00:00.000Z",
      "mts": "2025-12-29T12:00:00.000Z",
      "rev": 0,
      "uuObjectType": "appointment"
    },
    "oid": "693063296a854f19658293e9",
    "id": "693063296a854f19658293e9"
  }
]
